blech/__init__.py
blech/__main__.py
blech/config_defaults.py
blech/main.py
blech/models.py
blech/scraper.py
blech-0.3.0.dist-info/LICENSE
blech-0.3.0.dist-info/METADATA
blech-0.3.0.dist-info/WHEEL
blech-0.3.0.dist-info/entry_points.txt
blech-0.3.0.dist-info/RECORD
