Metadata-Version: 2.3
Name: blech
Version: 0.3.0
Summary: BLECH is a tool designed to automatically identify and extract links to individual posts from a blog's main page, index, or feed. After identifying the links, it proceeds to fetch and parse the content of each blog post, making it easier to process, analyze, or archive blog data.
License: MIT
Keywords: blog,scraper,content extraction,web scraping,cli
Author: jkarenko
Author-email: juho.karenko@gmail.com
Requires-Python: >=3.9,<4.0
Classifier: Development Status :: 3 - Alpha
Classifier: Environment :: Console
Classifier: Intended Audience :: Developers
Classifier: Intended Audience :: End Users/Desktop
Classifier: License :: OSI Approved :: MIT License
Classifier: Programming Language :: Python :: 3
Classifier: Programming Language :: Python :: 3.9
Classifier: Programming Language :: Python :: 3.10
Classifier: Programming Language :: Python :: 3.11
Classifier: Programming Language :: Python :: 3.12
Classifier: Programming Language :: Python :: 3.13
Classifier: Topic :: Internet :: WWW/HTTP
Classifier: Topic :: Text Processing
Classifier: Topic :: Utilities
Requires-Dist: beautifulsoup4 (>=4.12.3,<5.0.0)
Requires-Dist: requests (>=2.32.3,<3.0.0)
Project-URL: Homepage, https://github.com/jkarenko/blog-crawler
Project-URL: Repository, https://github.com/jkarenko/blog-crawler
